{
  "version": "0.2",
  "language": "en-GB",
  "ignorePaths": [
    "Cargo.toml",
    "Cargo.lock",
    "target/**",
    "Justfile",
    "**/Justfile",
    "Dockerfile"
  ],
  "words": [
    "Adnane",
    "Ahmad",
    "analyzer",
    "Antwi",
    "axum",
    "bigserial",
    "Burgun",
    "cfgs",
    "Choo",
    "chrono",
    "clippy",
    "color",
    "compile_protos",
    "Coulet",
    "createuser",
    "defenses",
    "DICOM",
    "docsrs",
    "dtolnay",
    "Dwarnings",
    "euxo",
    "favor",
    "FHIR",
    "fullstorydev",
    "getifaddr",
    "gitehr",
    "gitrepo",
    "Goyal",
    "grpcui",
    "grpcurl",
    "healthcheck",
    "Hyperledger",
    "IPFS",
    "Justfile",
    "Kerrache",
    "Kulantuga",
    "libapi",
    "libvpr",
    "makedirs",
    "mdbook",
    "Mishra",
    "Mohandas",
    "MSRV",
    "MSVC",
    "noindex",
    "noncommercially",
    "nonmain",
    "noscript",
    "nullglob",
    "O_RDONLY",
    "offs",
    "omics",
    "Ommix",
    "onprem",
    "Parmar",
    "PGPASSWORD",
    "PGURL",
    "pipefail",
    "POMR",
    "prost",
    "protoc",
    "protos",
    "PROV",
    "psql",
    "psql_ok",
    "Reen",
    "Rehman",
    "resp",
    "rgba",
    "Roboto",
    "rustc",
    "rustdoc",
    "RUSTDOCFLAGS",
    "rustup",
    "Segoe",
    "serde",
    "shopt",
    "Szilagyi",
    "timestamptz",
    "tlsv",
    "Tunables",
    "Utoipa",
    "vars",
    "Venkaresan"
  ],
  "ignoreWords": ["Exampletown"],
  "languageSettings": [
    {
      "languageId": "rust",
      "includeRegExpList": ["string", "comment", "doc"]
    },
    {
      "languageId": "markdown",
      "includeRegExpList": [".*"]
    }
  ]
}
